prompt_deck/__init__.py
prompt_deck/__main__.py
prompt_deck/context_input.py
prompt_deck/file_drop_area.py
prompt_deck/file_placeholder.py
prompt_deck/prompt_deck.py
prompt_deck/styles.py
prompt_deck-0.1.0.dist-info/METADATA
prompt_deck-0.1.0.dist-info/WHEEL
prompt_deck-0.1.0.dist-info/entry_points.txt
prompt_deck-0.1.0.dist-info/licenses/LICENSE
prompt_deck-0.1.0.dist-info/RECORD
