Metadata-Version: 2.4
Name: prompt-deck
Version: 0.1.0
Summary: A lightweight Windows utility for structuring LLM prompts
Author-email: yada <trojblue@gmail.com>
License-Expression: MIT
License-File: LICENSE
Requires-Python: >=3.8
Requires-Dist: appdirs>=1.4.4
Requires-Dist: keyboard>=0.13.5
Requires-Dist: pyqt6>=6.6.1
